<?xml version="1.0" encoding="UTF-8"?>
<DCOPData Simulator="hpeesofsim" Time="Tue Mar 10 14:21:44 2026" Version="1.0">
 <Controller name="SP1">
  <SweepCondition>
   <P>freq: 4.0000000000000000e+08</P>
  </SweepCondition>
  <DC_OPDeclaration/>
  <DC_Voltages>
   <V>0: 0.0000000000000000e+00</V>
   <V>D10.N__0: 0.0000000000000000e+00</V>
   <V>D10.N__1: 0.0000000000000000e+00</V>
   <V>D10.N__2: 0.0000000000000000e+00</V>
   <V>D10.N__3: 0.0000000000000000e+00</V>
   <V>D10.N__4: 0.0000000000000000e+00</V>
   <V>D10.N__5: 0.0000000000000000e+00</V>
   <V>D10.N__6: 0.0000000000000000e+00</V>
   <V>D11.N__0: 0.0000000000000000e+00</V>
   <V>D11.N__1: 0.0000000000000000e+00</V>
   <V>D11.N__2: 0.0000000000000000e+00</V>
   <V>D11.N__3: 0.0000000000000000e+00</V>
   <V>D11.N__4: 0.0000000000000000e+00</V>
   <V>D11.N__5: 0.0000000000000000e+00</V>
   <V>D11.N__6: 0.0000000000000000e+00</V>
   <V>N__35: 0.0000000000000000e+00</V>
   <V>N__36: 0.0000000000000000e+00</V>
   <V>N__47: 0.0000000000000000e+00</V>
   <V>N__48: 0.0000000000000000e+00</V>
   <V>N__49: 0.0000000000000000e+00</V>
   <V>N__50: 0.0000000000000000e+00</V>
   <V>SNP1.p0: 0.0000000000000000e+00</V>
   <V>SNP1.p1: 0.0000000000000000e+00</V>
   <V>SNP1.p2: 0.0000000000000000e+00</V>
   <V>SNP2.p0: 0.0000000000000000e+00</V>
   <V>SNP2.p1: 0.0000000000000000e+00</V>
   <V>SNP2.p2: 0.0000000000000000e+00</V>
   <V>SNP5.p0: 0.0000000000000000e+00</V>
   <V>SNP5.p1: 0.0000000000000000e+00</V>
   <V>SNP5.p2: 0.0000000000000000e+00</V>
   <V>SNP6.p0: 0.0000000000000000e+00</V>
   <V>SNP6.p1: 0.0000000000000000e+00</V>
   <V>SNP6.p2: 0.0000000000000000e+00</V>
   <GV>0: 0.0000000000000000e+00</GV>
  </DC_Voltages>
  <DC_PinCurrents>
   <I>D10: 0.0000000000000000e+00, 0.0000000000000000e+00</I>
   <I>D11: 0.0000000000000000e+00, 0.0000000000000000e+00</I>
   <I>R1: 0.0000000000000000e+00, 0.0000000000000000e+00</I>
   <I>SNP1: 0.0000000000000000e+00, 0.0000000000000000e+00, 0.0000000000000000e+00</I>
   <I>SNP2: 0.0000000000000000e+00, 0.0000000000000000e+00, 0.0000000000000000e+00</I>
   <I>SNP5: 0.0000000000000000e+00, 0.0000000000000000e+00, 0.0000000000000000e+00</I>
   <I>SNP6: 0.0000000000000000e+00, 0.0000000000000000e+00, 0.0000000000000000e+00</I>
   <I>SRC1: 0.0000000000000000e+00, 0.0000000000000000e+00</I>
   <I>TermG1: 0.0000000000000000e+00, 0.0000000000000000e+00</I>
   <I>TermG2: 0.0000000000000000e+00, 0.0000000000000000e+00</I>
  </DC_PinCurrents>
  <DC_OPInstances/>
 </Controller>
</DCOPData>
